.gitignore
LICENSE
README.md
pyproject.toml
setup.py
JWaves.egg-info/PKG-INFO
JWaves.egg-info/SOURCES.txt
JWaves.egg-info/dependency_links.txt
JWaves.egg-info/requires.txt
JWaves.egg-info/top_level.txt
src/MagneticFormFactor.py
src/RPA.py
src/S02_firstTestsB.py
src/S08_extensionTest.py
src/formFactorScraper.py
src/pythonVersion.py
src/s01_example.py
src/s02_firstTests.py
src/s05_scenarios.py
src/s07_exampleNi3TeO6.py
src/s07_exampleNi3TeO6_simplified.py
src/s07_exampleNi3TeO6_simplifiedV2.py
src/s09_SimplifiedSetup.py
src/s10_SpinW.py
src/s10_SpinWV2.py